half_adder.sv
module half_adder(
    input logic i1, i2,
    output logic carry, sum
);
    assign sum = i1^i2;
    assign carry = i1 & i2;
    endmodule
module full_adder(
    input logic i1, i2,
    input logic cin,
    output carry, 
    output sum
);
    logic s1, s2, c1, c2;
    half_adder h1(i1, i2, c1, s1);
    half_adder h2(s1, cin, c2, sum);
    assign carry = c1 | c2;
    endmodule

full_adder_tb.sv
`include "half_adder.sv"
module full_adder_tb();
    logic i1, i2, cin, sum, carry;
    full_adder uut(i1, i2, cin, carry, sum);
    initial begin
        $dumpfile("waves_full_adder.vcd");
        $dumpvars(0, full_adder_tb);
        i1 = 1'b0; i2 = 1'b0; cin = 1'b0; #10;
        i1 = 1'b0; i2 = 1'b0; cin = 1'b1; #10;
        i1 = 1'b0; i2 = 1'b1; cin = 1'b0; #10;
        i1 = 1'b0; i2 = 1'b1; cin = 1'b1; #10;
        i1 = 1'b1; i2 = 1'b0; cin = 1'b0; #10;
        i1 = 1'b1; i2 = 1'b0; cin = 1'b1; #10;
        i1 = 1'b1; i2 = 1'b1; cin = 1'b0; #10;
        i1 = 1'b1; i2 = 1'b1; cin = 1'b1; #10;
        $finish;
    end
endmodule

waves_full_adder.vcd
$date
	Tue Feb 17 14:28:57 2026
$end
$version
	Icarus Verilog
$end
$timescale
	1s
$end
$scope module full_adder_tb $end
$var wire 1 ! sum $end
$var wire 1 " carry $end
$var reg 1 # cin $end
$var reg 1 $ i1 $end
$var reg 1 % i2 $end
$scope module uut $end
$var wire 1 " carry $end
$var wire 1 # cin $end
$var wire 1 $ i1 $end
$var wire 1 % i2 $end
$var wire 1 ! sum $end
$var wire 1 & s1 $end
$var wire 1 ' c2 $end
$var wire 1 ( c1 $end
$scope module h1 $end
$var wire 1 ( carry $end
$var wire 1 $ i1 $end
$var wire 1 % i2 $end
$var wire 1 & sum $end
$upscope $end
$scope module h2 $end
$var wire 1 ' carry $end
$var wire 1 & i1 $end
$var wire 1 # i2 $end
$var wire 1 ! sum $end
$upscope $end
$upscope $end
$upscope $end
$enddefinitions $end
$comment Show the parameter values. $end
$dumpall
$end
#0
$dumpvars
0(
0'
0&
0%
0$
0#
0"
0!
$end
#10
1!
1#
#20
1&
0#
1%
#30
1"
0!
1'
1#
#40
0"
1!
0'
0#
0%
1$
#50
1"
0!
1'
1#
#60
0'
0&
1(
0#
1%
#70
1!
1#
